ollama_x_client/__init__.py
ollama_x_client/api/__init__.py
ollama_x_client/api/continue_dev/__init__.py
ollama_x_client/api/continue_dev/all.py
ollama_x_client/api/continue_dev/create.py
ollama_x_client/api/continue_dev/edit/__init__.py
ollama_x_client/api/continue_dev/edit/context_providers.py
ollama_x_client/api/continue_dev/edit/embeddings.py
ollama_x_client/api/continue_dev/edit/models.py
ollama_x_client/api/continue_dev/edit/tab_autocomplete_model.py
ollama_x_client/api/continue_dev/edit/tab_autocomplete_options.py
ollama_x_client/api/continue_dev/join.py
ollama_x_client/api/continue_dev/one.py
ollama_x_client/api/continue_dev/reset_invite_id.py
ollama_x_client/api/continue_dev/sync.py
ollama_x_client/api/server/__init__.py
ollama_x_client/api/server/all.py
ollama_x_client/api/server/create.py
ollama_x_client/api/server/delete.py
ollama_x_client/api/server/one.py
ollama_x_client/api/server/update.py
ollama_x_client/api/user/__init__.py
ollama_x_client/api/user/all.py
ollama_x_client/api/user/create.py
ollama_x_client/api/user/delete.py
ollama_x_client/api/user/one.py
ollama_x_client/api/user/register.py
ollama_x_client/api/user/reset_key.py
ollama_x_client/client.py
ollama_x_client/errors.py
ollama_x_client/models/__init__.py
ollama_x_client/models/api_error_access_denied.py
ollama_x_client/models/api_error_details.py
ollama_x_client/models/api_error_details_code.py
ollama_x_client/models/api_server.py
ollama_x_client/models/api_server_models_item.py
ollama_x_client/models/base_completion_options.py
ollama_x_client/models/code_context_provider.py
ollama_x_client/models/code_context_provider_name.py
ollama_x_client/models/codebase_context_provider.py
ollama_x_client/models/codebase_context_provider_name.py
ollama_x_client/models/continue_config.py
ollama_x_client/models/create_project_request.py
ollama_x_client/models/create_user_request.py
ollama_x_client/models/custom_command.py
ollama_x_client/models/diff_context_provider.py
ollama_x_client-0.1.0.dist-info/METADATA
ollama_x_client-0.1.0.dist-info/WHEEL
ollama_x_client-0.1.0.dist-info/RECORD
