Metadata-Version: 2.1
Name: ollama-x-client
Version: 0.1.0
Summary: 
Author: Yurzs
Author-email: yurzs@icloud.com
Requires-Python: >=3.12,<4
Classifier: Programming Language :: Python :: 3
Classifier: Programming Language :: Python :: 3.12
Requires-Dist: attrs (>=24.2.0,<25.0.0)
Requires-Dist: httpx (>=0.27.0,<0.28.0)
